opinionated_configparser/__init__.py
opinionated_configparser-1.0.2.dist-info/licenses/LICENSE
opinionated_configparser-1.0.2.dist-info/METADATA
opinionated_configparser-1.0.2.dist-info/WHEEL
opinionated_configparser-1.0.2.dist-info/top_level.txt
opinionated_configparser-1.0.2.dist-info/RECORD
