Metadata-Version: 2.4
Name: opinionated_configparser
Version: 1.0.2
Summary: opinionated python configparser library override to deal with configuration variants (PROD, DEV...) and jija2 interpolation
Home-page: https://github.com/metwork-framework/opinionated_configparser
Author: Fabien MARTY
Author-email: fabien.marty@gmail.com
License: MIT
Keywords: configparser extension
Classifier: License :: OSI Approved :: MIT License
Classifier: Intended Audience :: Developers
Classifier: Programming Language :: Python :: 2.7
Classifier: Programming Language :: Python :: 3
Requires-Python: >=2.7
License-File: LICENSE
Requires-Dist: jinja2
Dynamic: author
Dynamic: author-email
Dynamic: classifier
Dynamic: description
Dynamic: description-content-type
Dynamic: home-page
Dynamic: keywords
Dynamic: license
Dynamic: license-file
Dynamic: requires-dist
Dynamic: requires-python
Dynamic: summary
